mcp_postgresql_ops/__init__.py
mcp_postgresql_ops/__main__.py
mcp_postgresql_ops/functions.py
mcp_postgresql_ops/mcp_main.py
mcp_postgresql_ops/version_compat.py
mcp_postgresql_ops-3.1.2.dist-info/licenses/LICENSE
mcp_postgresql_ops-3.1.2.dist-info/METADATA
mcp_postgresql_ops-3.1.2.dist-info/WHEEL
mcp_postgresql_ops-3.1.2.dist-info/entry_points.txt
mcp_postgresql_ops-3.1.2.dist-info/top_level.txt
mcp_postgresql_ops-3.1.2.dist-info/RECORD
